README.md
setup.py
simplejwt/__init__.py
simplejwt/exception.py
simplejwt/jwt.py
simplejwt/util.py
simplejwt.egg-info/PKG-INFO
simplejwt.egg-info/SOURCES.txt
simplejwt.egg-info/dependency_links.txt
simplejwt.egg-info/requires.txt
simplejwt.egg-info/top_level.txt