Metadata-Version: 2.1
Name: simplejwt
Version: 0.1.0
Summary: A dead simple JWT library
Home-page: https://github.com/jmwri/simplejwt
Author: Jim Wright
Author-email: jmwri93@gmail.com
License: MIT
Download-URL: https://github.com/jmwri/simplejwt/archive/0.1.0.tar.gz
Keywords: python,jwt,simple,simplejwt
Platform: UNKNOWN
Classifier: Development Status :: 3 - Alpha
Classifier: Intended Audience :: Developers
Classifier: Topic :: Software Development
Classifier: License :: OSI Approved :: MIT License
Classifier: Programming Language :: Python :: 3.6
Requires-Python: >=3.6, <4
Provides-Extra: test
